CHANGELOG
LICENSE
MANIFEST.in
setup.py
apiclient/__init__.py
google_api_python_client_uritemplate.egg-info/PKG-INFO
google_api_python_client_uritemplate.egg-info/SOURCES.txt
google_api_python_client_uritemplate.egg-info/dependency_links.txt
google_api_python_client_uritemplate.egg-info/requires.txt
google_api_python_client_uritemplate.egg-info/top_level.txt
googleapiclient/__init__.py
googleapiclient/channel.py
googleapiclient/discovery.py
googleapiclient/errors.py
googleapiclient/http.py
googleapiclient/mimeparse.py
googleapiclient/model.py
googleapiclient/sample_tools.py
googleapiclient/schema.py
googleapiclient/discovery_cache/__init__.py
googleapiclient/discovery_cache/appengine_memcache.py
googleapiclient/discovery_cache/base.py
googleapiclient/discovery_cache/file_cache.py