Metadata-Version: 1.1
Name: google-api-python-client-uritemplate
Version: 1.4.2
Summary: Google API Client Library for Python (uritemplate.py compatibility fork)
Home-page: http://github.com/venmo/google-api-python-client-uritemplate/
Author: Google Inc.
Author-email: UNKNOWN
License: Apache 2.0
Keywords: google api client
Platform: UNKNOWN
Classifier: Programming Language :: Python :: 2
Classifier: Programming Language :: Python :: 2.6
Classifier: Programming Language :: Python :: 2.7
Classifier: Programming Language :: Python :: 3
Classifier: Programming Language :: Python :: 3.3
Classifier: Programming Language :: Python :: 3.4
Classifier: Development Status :: 5 - Production/Stable
Classifier: Intended Audience :: Developers
Classifier: License :: OSI Approved :: Apache Software License
Classifier: Operating System :: OS Independent
Classifier: Topic :: Internet :: WWW/HTTP
